{
  "groups": [
    {
      "id": "alcohols",
      "name": "Alcohols",
      "inclusions": ["alcohol"]
    },
    {
      "id": "preservatives",
      "name": "Preservatives",
      "inclusions": ["paraben"]
    },
    {
      "id": "detergents",
      "name": "Detergents",
      "inclusions": ["sulfate"]
    },
    {
      "id": "silicones",
      "name": "Silicones",
      "inclusions": ["silicone", "cone"],
      "defaultIngredient": "unknown_non-water-soluble_silicone"
    },
    {
      "id": "others",
      "name": "Others"
    },
    {
      "id": "waxes",
      "name": "Waxes"
    },
    {
      "id": "oils",
      "name": "Oils"
    }
  ]
}

